qapp_pennylane/__init__.py
qapp_pennylane/async_tasks/__init__.py
qapp_pennylane/async_tasks/pennylane_circuit_export_task.py
qapp_pennylane/component/__init__.py
qapp_pennylane/component/backend/__init__.py
qapp_pennylane/component/backend/pennylane_invocation.py
qapp_pennylane/factory/__init__.py
qapp_pennylane/factory/pennylane_device_factory.py
qapp_pennylane/factory/pennylane_handler_factory.py
qapp_pennylane/factory/pennylane_provider_factory.py
qapp_pennylane/handler/__init__.py
qapp_pennylane/handler/invocation_handler.py
qapp_pennylane/model/__init__.py
qapp_pennylane/model/device/__init__.py
qapp_pennylane/model/device/aws_braket_device.py
qapp_pennylane/model/device/ibm_quantum_device.py
qapp_pennylane/model/device/pennylane_device.py
qapp_pennylane/model/device/qapp_pennylane_device.py
qapp_pennylane/model/provider/__init__.py
qapp_pennylane/model/provider/aws_braket_provider.py
qapp_pennylane/model/provider/ibm_cloud_provider.py
qapp_pennylane/model/provider/ibm_quantum_provider.py
qapp_pennylane/model/provider/qapp_pennylane_provider.py
test_qapp_pennylane-0.0.1.dist-info/LICENSE
test_qapp_pennylane-0.0.1.dist-info/METADATA
test_qapp_pennylane-0.0.1.dist-info/WHEEL
test_qapp_pennylane-0.0.1.dist-info/top_level.txt
test_qapp_pennylane-0.0.1.dist-info/RECORD
